README.txt
setup.py
onedrive/__init__.py
onedrive/api_v5.py
onedrive/cli_tool.py
onedrive/conf.py
onedrive/portalocker.py
python_onedrive.egg-info/PKG-INFO
python_onedrive.egg-info/SOURCES.txt
python_onedrive.egg-info/dependency_links.txt
python_onedrive.egg-info/entry_points.txt
python_onedrive.egg-info/requires.txt
python_onedrive.egg-info/top_level.txt