Metadata-Version: 1.1
Name: python-onedrive
Version: 15.02.4
Summary: Python and command-line interface for Microsoft LiveConnect OneDrive REST API v5.0
Home-page: http://github.com/mk-fg/python-onedrive
Author: Mike Kazantsev, Antonio Chen
Author-email: mk.fraggod@gmail.com
License: WTFPL
Keywords: onedrive,skydrive,api,oauth2,rest,microsoft,cloud,live,liveconnect,json,storage,storage provider,file hosting
Platform: UNKNOWN
Classifier: Development Status :: 4 - Beta
Classifier: Environment :: Console
Classifier: Intended Audience :: Developers
Classifier: Intended Audience :: System Administrators
Classifier: Intended Audience :: Information Technology
Classifier: License :: OSI Approved
Classifier: Operating System :: OS Independent
Classifier: Programming Language :: Python
Classifier: Programming Language :: Python :: 2.7
Classifier: Programming Language :: Python :: 2 :: Only
Classifier: Topic :: Internet
Classifier: Topic :: Software Development
Classifier: Topic :: System :: Archiving
Classifier: Topic :: System :: Filesystems
Classifier: Topic :: Utilities
